<Page xmlns="http://www.nativescript.org/tns.xsd" 
      navigatedTo="navigatedTo">
  <Page.optionsMenu>
    <MenuItem text="{{ strings.save }}" tap="saveButtonTap" android.position="actionBar" />
  </Page.optionsMenu>
  <GridLayout rows="*, auto">
    <ScrollView>
      <GridLayout rows="auto, auto, auto, auto, auto, auto, auto, auto, auto">
        <TextField hint="Task name" text="{{ item.Name }}" cssClass="headerTextField"/>

        <GridLayout row="1" cssClass="detailsContainer">
          <StackLayout cssClass="pickerContainer" tap="projectPickerTap" >
            <Label text="Project" cssClass="pickerLabel" />
            <GridLayout columns="*, auto" cssClass="innerContainer" >
              <Label text="{{ project | getProjectNameForProjectsPicker }}" cssClass="pickerValue" />
              <Image col="1" src="res://ic_arrow_drop_down" cssClass="pickerIcon" stretch="none" />
            </GridLayout>
            <Border cssClass="pickerBorder" />
          </StackLayout>
        </GridLayout>
        
        <GridLayout row="2" columns="auto, 2*, *" cssClass="detailsContainer">
          <Image src="res://ic_duedate" cssClass="detailsIcon" stretch="none"/>

          <StackLayout col="1" cssClass="pickerContainer" tap="datePickerTap" >
            <Label text="Due date" cssClass="pickerLabel" />
            <GridLayout columns="*, auto" cssClass="innerContainer">
              <Label text="{{ item.DueDate | formatDate }}" cssClass="pickerValue" />
              <Image col="1" src="res://ic_arrow_drop_down" cssClass="pickerIcon" stretch="none" />
            </GridLayout>
            <Border cssClass="pickerBorder" />
          </StackLayout>

          <StackLayout col="2" margin="0 4 0 16" cssClass="pickerContainer" tap="timePickerTap" >
            <Label text="Time" cssClass="pickerLabel" />
            <GridLayout columns="*, auto" cssClass="innerContainer">
              <Label text="{{ item.DueDate  | formatTime }}" cssClass="pickerValue" />
              <Image col="1" src="res://ic_arrow_drop_down" cssClass="pickerIcon" stretch="none" />
            </GridLayout>
            <Border cssClass="pickerBorder" />
          </StackLayout>
        </GridLayout>

        <!--<GridLayout row="3" columns="auto, *" cssClass="detailsContainer">
          <Image src="res://ic_reminder" cssClass="detailsIcon" stretch="none"/>

          <StackLayout col="1" cssClass="pickerContainer" tap="reminderPickerTap" >
            <Label text="Reminder" cssClass="pickerLabel" />
            <GridLayout columns="*, auto" cssClass="innerContainer">
              <Label text="{{ item | formatReminder }}" cssClass="pickerValue" />
              <Image col="1" src="res://ic_arrow_drop_down" cssClass="pickerIcon" stretch="none" />
            </GridLayout>
            <Border cssClass="pickerBorder" />
          </StackLayout>
        </GridLayout>-->

        <GridLayout row="4" cssClass="detailsContainer" padding="8 16 8 16" columns="auto, *, auto" tap="takePictureButtonTap" >
          <Image src="res://ic_photo" cssClass="detailsIcon" stretch="none"/>
          <Label text="Tap to add photo" col="1" margin="0 0 0 4" />
          <Image col="2" stretch="fill" src="{{ picture }}" visibility="{{ picture ? 'visible' : 'collapsed' }}" cssClass="picturePreview" />
        </GridLayout>

        <GridLayout row="5" cssClass="detailsContainer" columns="auto, *" >
          <Image src="res://ic_phone" cssClass="detailsIcon" stretch="none" />
          <TextField keyboardType="number" hint="Contact phone" text="{{ item.Phone }}" col="1" cssClass="detailsTextField" />
        </GridLayout>

        <GridLayout row="6" cssClass="detailsContainer" columns="auto, *" >
          <Image src="res://ic_email" cssClass="detailsIcon" stretch="none" />
          <TextField keyboardType="email" hint="Contact email" text="{{ item.Email }}" col="1" cssClass="detailsTextField" />
        </GridLayout>

        <GridLayout row="7" cssClass="detailsContainer" columns="auto, *" >
          <Image src="res://ic_url" cssClass="detailsIcon" stretch="none" width="24" height="24"/>
          <TextField hint="url" keyboardType="url" text="{{ item.Url }}" col="1" cssClass="detailsTextField" />
        </GridLayout>

        <TextView row="8" hint="notes" text="{{ item.Notes }}" cssClass="notesTextView"/>
      </GridLayout>
    </ScrollView>

    <Button text="{{ strings.delete }}" row="1" tap="deleteButtonTap" cssClass="deleteButton" visibility="{{ editVisibility }}"/>

    <ActivityIndicator cssClass="activityIndicator" busy="{{ isLoading }}" />
  </GridLayout>
</Page>